pyori/__init__.py
pyori/animator.py
pyori/axioms.py
pyori/convert.py
pyori/fold.py
pyori/foldfile.py
pyori/foldsim.py
pyori/geometry.py
pyori/graph.py
pyori/layer.py
pyori/layout.py
pyori/save.py
pyori/svg.py
pyori/swomp_interface.py
pyori/utils.py
pyori/veiwer.py
pyori/vertex.py
pyori-0.1.0.dist-info/licenses/LICENSE
pyori-0.1.0.dist-info/METADATA
pyori-0.1.0.dist-info/WHEEL
pyori-0.1.0.dist-info/top_level.txt
pyori-0.1.0.dist-info/RECORD
