Metadata-Version: 2.4
Name: PyOri
Version: 0.1.0
Summary: A Pure Python Library for Computational Origami
Author-email: Pooja Thaker <ppthaker1@gmail.com>
License-Expression: MIT
Project-URL: Homepage, https://github.com/Happy-Birdie/OriPy
Project-URL: Documentation, https://github.com/Happy-Birdie/OriPy
Requires-Python: >=3.8
License-File: LICENSE
Requires-Dist: numpy
Requires-Dist: scipy
Requires-Dist: matplotlib
Dynamic: license-file
